odoo8_addon_users_ldap_mail-8.0.1.0.0.99.dev12-nspkg.pth
odoo_addons/users_ldap_mail/__init__.py
odoo_addons/users_ldap_mail/__openerp__.py
odoo_addons/users_ldap_mail/users_ldap_model.py
odoo_addons/users_ldap_mail/users_ldap_view.xml
odoo_addons/users_ldap_mail/i18n/de.po
odoo_addons/users_ldap_mail/i18n/es.po
odoo_addons/users_ldap_mail/i18n/fr.po
odoo_addons/users_ldap_mail/i18n/hr.po
odoo_addons/users_ldap_mail/i18n/it.po
odoo_addons/users_ldap_mail/i18n/pt_BR.po
odoo_addons/users_ldap_mail/i18n/sl.po
odoo_addons/users_ldap_mail/i18n/tr.po
odoo_addons/users_ldap_mail/i18n/users_ldap_mail.pot
odoo_addons/users_ldap_mail/static/description/icon.png
odoo8_addon_users_ldap_mail-8.0.1.0.0.99.dev12.dist-info/METADATA
odoo8_addon_users_ldap_mail-8.0.1.0.0.99.dev12.dist-info/WHEEL
odoo8_addon_users_ldap_mail-8.0.1.0.0.99.dev12.dist-info/namespace_packages.txt
odoo8_addon_users_ldap_mail-8.0.1.0.0.99.dev12.dist-info/top_level.txt
odoo8_addon_users_ldap_mail-8.0.1.0.0.99.dev12.dist-info/RECORD
